{
    "code": "COSJ100132+020533",
    "ra": "150.3854624746602",
    "dec": "2.092556920514117",
    "score": "S04",
    "ranking": "ABBXXX",
    "primary_waveband": "F277W",
    "mask_radius": 2.8,
    "mask_radius_small": 2.8,
    "visual_1_type": "edge",
    "data_field": "A5",
    "catalogue_number": "148985",
    "lens_spec_z": 0.9017468690872192,
    "lens_spec_z_source": "DESI-SV3-LRG",
    "lens_cw_photo_z_med": 0.8952,
    "lens_cw_photo_z_L68": 0.89,
    "lens_cw_photo_U_L68": 0.9115,
    "lens_cw_stmass_med": 11.00002,
    "lens_cw_stmass_L68": 10.96598,
    "lens_cw_stmass_U68": 11.05
}